classic/executor/__init__.py
classic/executor/executor.py
classic_thread_pool_executor-1.1.1.dist-info/licenses/LICENSE
classic_thread_pool_executor-1.1.1.dist-info/METADATA
classic_thread_pool_executor-1.1.1.dist-info/WHEEL
classic_thread_pool_executor-1.1.1.dist-info/top_level.txt
classic_thread_pool_executor-1.1.1.dist-info/RECORD
