Metadata-Version: 2.4
Name: classic-thread-pool-executor
Version: 1.1.1
Summary: Simple threadpool executor without futures
Author-email: Sergey Variasov <variasov@gmail.com>
Project-URL: Homepage, https://github.com/variasov/classic-thread-pool-executor
Requires-Python: >=3.10
License-File: LICENSE
Provides-Extra: dev
Requires-Dist: build~=1.2.2.post1; extra == "dev"
Requires-Dist: pytest==8.3.4; extra == "dev"
Requires-Dist: pytest-cov==6.0.0; extra == "dev"
Requires-Dist: twine~=4.0; extra == "dev"
Dynamic: license-file
